hac_img.py
hac_img-0.0.1.dist-info/LICENSE.txt
hac_img-0.0.1.dist-info/METADATA
hac_img-0.0.1.dist-info/WHEEL
hac_img-0.0.1.dist-info/top_level.txt
hac_img-0.0.1.dist-info/RECORD
