Metadata-Version: 2.1
Name: hac-img
Version: 0.0.1
Summary: Hierarchical clustering algorithm for image clustering using Scikit-Image
Home-page: https://mharish.dev
Author: Harish Mohan
Author-email: mharish2797@gmail.com
License: MIT
Download-URL: https://github.com/mharish2797/hac_img/archive/0.0.1.tar.gz
Keywords: image,hierarchical,clustering
Platform: UNKNOWN
Requires-Dist: scikit-image
Requires-Dist: numpy
Requires-Dist: Pillow
